awscpsaml/__init__.py
awscpsaml/awscp.py
aws_cp_saml-0.0.2.dist-info/LICENSE
aws_cp_saml-0.0.2.dist-info/METADATA
aws_cp_saml-0.0.2.dist-info/WHEEL
aws_cp_saml-0.0.2.dist-info/entry_points.txt
aws_cp_saml-0.0.2.dist-info/top_level.txt
aws_cp_saml-0.0.2.dist-info/RECORD
