Metadata-Version: 2.1
Name: aws-cp-saml
Version: 0.0.2
Summary: AWS SAML Credentials Process CLI that uses Windows SSO (Integrated Windows Authentication)
Home-page: https://github.com/roberthutto/aws-cp-saml
Author: Robert Hutto
Author-email: rdhutto1@gmail.com
License: Apache 2
Keywords: SAML SSO IWA AWS credentials ntlm kerberos windows
Platform: Windows
Classifier: Development Status :: 4 - Beta
Classifier: Environment :: Win32 (MS Windows)
Classifier: Intended Audience :: Developers
Classifier: Topic :: Internet
Classifier: License :: OSI Approved :: MIT License
Classifier: Natural Language :: English
Classifier: Operating System :: Microsoft :: Windows
Classifier: Programming Language :: Python :: 2.7
Classifier: Programming Language :: Python :: 3
Classifier: Programming Language :: Python :: 3.3
Classifier: Programming Language :: Python :: 3.4
Classifier: Programming Language :: Python :: 3.5
Classifier: Programming Language :: Python :: 3.6
Classifier: Programming Language :: Python :: 3.7
Classifier: Programming Language :: Python :: 3.8
Requires-Dist: setuptools
Requires-Dist: python-dateutil
Requires-Dist: botocore
Requires-Dist: beautifulsoup4
Requires-Dist: boto3
Requires-Dist: requests
Requires-Dist: requests-negotiate-sspi
